chatgpt_client.py
chatgpt_client-0.2.0.dist-info/LICENSE
chatgpt_client-0.2.0.dist-info/METADATA
chatgpt_client-0.2.0.dist-info/WHEEL
chatgpt_client-0.2.0.dist-info/RECORD
