Metadata-Version: 2.1
Name: chatgpt-client
Version: 0.2.0
Summary: Python client for the unofficial ChatGPT API.
License: MIT
Author: vsakkas
Author-email: vasileios.sakkas96@gmail.com
Requires-Python: >=3.10,<4.0
Classifier: License :: OSI Approved :: MIT License
Classifier: Programming Language :: Python :: 3
Classifier: Programming Language :: Python :: 3.10
Classifier: Programming Language :: Python :: 3.11
Requires-Dist: aiohttp (>=3.8.3,<4.0.0)
